bin/__init__.py
bin/aliases.py
bin/aliasesv2.py
bin/apihandler.py
bin/application_directories.py
bin/balance_nogui.py
bin/bismuth.py
bin/bisnode.py
bin/bisurl.py
bin/cmd_addpeers.py
bin/commands.py
bin/connectionmanager.py
bin/connections.py
bin/dbhandler.py
bin/demo_getaddresssince.py
bin/demo_getstatus.py
bin/difficulty.py
bin/digest.py
bin/essentials.py
bin/fork.py
bin/genesis.py
bin/hmac_drbg.py
bin/hyperlane.py
bin/hyperlane_asyncio.py
bin/ledger_explorer.py
bin/log.py
bin/lwbench.py
bin/mempool.py
bin/mining.py
bin/mining_heavy3.py
bin/node_stop.py
bin/options.py
bin/peershandler.py
bin/plugins.py
bin/process_search.py
bin/quantizer.py
bin/recovery.py
bin/regnet.py
bin/rewards_reindex.py
bin/rewards_test.py
bin/send_csv.py
bin/send_nogui.py
bin/send_nogui_noconf.py
bin/simplecrypt.py
bin/staking.py
bin/tokensv2.py
bin/wallet.py
bin/wallet_async.py
bin/wallet_keys.py
bin/worker.py
bin/libs/__init__.py
bin/libs/client.py
bin/libs/keys.py
bin/libs/logger.py
bin/libs/node.py
bin/polysign/__init__.py
bin/polysign/signer.py
bin/polysign/signer_btc.py
bin/polysign/signer_crw.py
bin/polysign/signer_ecdsa.py
bin/polysign/signer_ed25519.py
bin/polysign/signer_rsa.py
bin/polysign/signerfactory.py
bin/static/__init__.py
bin/static/backup.py
bin/static/migrate.py
bin/static/tar.py
bin/static/tar_testnet.py
bin/static/untar.py
bisnode-0.0.2.data/scripts/bismuth.py
files/__init__.py
files/aliases.py
files/aliasesv2.py
files/apihandler.py
files/application_directories.py
files/balance_nogui.py
files/bisnode.py
files/bisurl.py
files/cmd_addpeers.py
files/commands.py
files/connectionmanager.py
files/connections.py
files/dbhandler.py
files/demo_getaddresssince.py
files/demo_getstatus.py
files/difficulty.py
files/digest.py
files/essentials.py
files/fork.py
files/genesis.py
files/hmac_drbg.py
files/hyperlane.py
files/hyperlane_asyncio.py
files/ledger_explorer.py
files/log.py
files/lwbench.py
files/mempool.py
files/mining.py
files/mining_heavy3.py
files/node.py
files/node_stop.py
bisnode-0.0.2.dist-info/LICENSE
bisnode-0.0.2.dist-info/METADATA
bisnode-0.0.2.dist-info/WHEEL
bisnode-0.0.2.dist-info/top_level.txt
bisnode-0.0.2.dist-info/RECORD
