Metadata-Version: 2.1
Name: bisnode
Version: 0.0.2
Summary: Bismuth Node
Home-page: https://github.com/bismuthfoundation/Bismuth
Author: Bismuth Foundation
Author-email: admin@bismuth.cz
License: UNKNOWN
Platform: UNKNOWN
Classifier: Programming Language :: Python :: 3.7
Classifier: License :: OSI Approved :: GNU General Public License v3 (GPLv3)
Classifier: Operating System :: OS Independent
Requires-Dist: PySocks
Requires-Dist: pycryptodomex
Requires-Dist: pillow
Requires-Dist: pyqrcode
Requires-Dist: matplotlib
Requires-Dist: ed25519
Requires-Dist: base58
Requires-Dist: coincurve
